solr_to_es/__init__.py
solr_to_es/__main__.py
solr_to_es/solrSource.py
pds.solr_to_es-0.3.0.dist-info/LICENSE.txt
pds.solr_to_es-0.3.0.dist-info/METADATA
pds.solr_to_es-0.3.0.dist-info/WHEEL
pds.solr_to_es-0.3.0.dist-info/entry_points.txt
pds.solr_to_es-0.3.0.dist-info/top_level.txt
pds.solr_to_es-0.3.0.dist-info/RECORD
