Metadata-Version: 2.1
Name: pds.solr-to-es
Version: 0.3.0
Summary: Export Solr Nodes to Elasticsearch Indexes
Home-page: https://github.com/o19s/solr-to-es
Author: Scott Stults
Author-email: sstults@opensourceconnections.com
License: Apache License, Version 2.0
Keywords: solr elasticsearch o19s
Classifier: Development Status :: 3 - Alpha
Classifier: Environment :: Console
Classifier: Intended Audience :: Developers
Classifier: Intended Audience :: System Administrators
Classifier: License :: OSI Approved :: Apache Software License
Classifier: Natural Language :: English
Classifier: Programming Language :: Python :: 2
Classifier: Programming Language :: Python :: 2.6
Classifier: Programming Language :: Python :: 2.7
Classifier: Programming Language :: Python :: 3.6
Classifier: Topic :: Utilities
License-File: LICENSE.txt
Requires-Dist: elasticsearch (<7.0.0,>=6.0.0)
